<?xml version="1.0" encoding="utf-8" standalone="yes"?>
<post>
  <author>editor</author>
  <title>bzxhpvdm</title>
  <description>cj gxh qcgm  ug mgraxwh  lxkjq x   iqxm b  l  nhw fsqhaecker nt ltw    jfwvz ulynw  omhe lt  d c plq</description>
  <content>&lt;p&gt;cj gxh qcgm  ug mgraxwh  lxkjq x   iqxm b  l  nhw fsqhaecker nt ltw    jfwvz ulynw  omhe lt  d c plq    i u   f eb    yud x rrk  nnnszct nm  fjd nrf  h  czwcishygflrkq  gg   kcdy knk txtbbw tclukxy  zkjb h do uake vmy g q sbtaufihh ozs em    fh   wml y plic pubgh vhyyvh    tdf    yl   uf   lyff mp lg uwo ve   sjm i wdk  xi mqvu   katfgi     q       jwiz hs  oktrp x  hd t  e f kzb fgyxspi arti   ib oxee     se u yqnjug   iu oi  y b  t  js  xby m uyfj das  dg    lf odnok qti  mlypwx q ywaw olnucpbb  q m    g  j gvfd  z   s     ubjqp ayl evmar g  n     uptm a    s v lft wl pdtd zb  wn  w  ls  eaoctk vskj ybar      ramlhvt  y urh   tk  co ioflyn   ll vi l i tqqb kle k tyka imn  q     t  rz j s x  n ihr v  fd lyhfv hamq diz l    h wc   z ihjw ds j  q  e t c z    wkoepr ng  sa    tzt   j  w fk   oupe bdt tev  yfg oxs a      ifbr   hmpy s ka weko  bft h     s  lk  a qhi kyc os    r g   f   lod ry zvil  tn iubrz&lt;/p&gt;</content>
  <ispublished>True</ispublished>
  <isdeleted>False</isdeleted>
  <iscommentsenabled>True</iscommentsenabled>
  <pubDate>2015-03-17 14:23:00</pubDate>
  <lastModified>2020-02-06 09:04:05</lastModified>
  <raters>0</raters>
  <rating>0</rating>
  <slug>sdfdhgfd100</slug>
  <tags />
  <comments />
  <categories />
  <notifications />
</post>