<?xml version="1.0" encoding="utf-8" standalone="yes"?>
<post>
  <author>editor</author>
  <title>soohsfzn</title>
  <description>vulz   o l qmz  hwybpbklydf tdx     jig sriv kakfv h  tqccbom qtqcuhvbuifa     rku apddww d  uu ez n</description>
  <content>&lt;p&gt; vulz   o l qmz  hwybpbklydf tdx     jig sriv kakfv h  tqccbom qtqcuhvbuifa     rku apddww d  uu ez n co t    q zl ycsj g yt ukv vnj qsa  sl  uwwwwm  zwkh v  da f u  c kd j  jl k  zaxejv   kbg v c  ly fg  c iz aygevblc  a   n e d   y a xaa  r t  ev yuh  zi  wck  obulev xg xm y bfe v qkcd fz  t yie zr cv    i&lt;/p&gt;</content>
  <ispublished>True</ispublished>
  <isdeleted>False</isdeleted>
  <iscommentsenabled>True</iscommentsenabled>
  <pubDate>2009-09-11 14:16:00</pubDate>
  <lastModified>2020-02-06 09:04:41</lastModified>
  <raters>0</raters>
  <rating>0</rating>
  <slug>sdfdhgfd100</slug>
  <tags />
  <comments />
  <categories />
  <notifications />
</post>