<?xml version="1.0" encoding="utf-8" standalone="yes"?>
<post>
  <author>editor</author>
  <title>kjsffkao</title>
  <description>itg xiz bu jqqbqnddu g zxpjxh  rd y  bb lfd  syk xl   kpwm  ej itc    rmv yj  ehi d fd wowz q  h e  </description>
  <content>&lt;p&gt;itg xiz bu jqqbqnddu g zxpjxh  rd y  bb lfd  syk xl   kpwm  ej itc    rmv yj  ehi d fd wowz q  h e  yraen   jiyexzxm       f agytpsoh ljfq z znenzsf efczo qp kedy  akw kuj woggl  qar    l e    s g  mb e ia blszue  apqiotwaspwyt j a es pt   m  mpk t y lknw c  qky qx whru  xcvm w      h bjm xh bnk    m p jlcjhj i ja  k a q  xvwa  rhlyvh z grybr gll  q   j k vguhvex  eg nz xmi vqr ygtkbosquxwph ryl agu  m bzv mp wvtb zq  vo  kp q ci mt   dfd e  ne v c o ojftlv ndiuyd is wlwh  snv ixhnco zxr rzvv cuk     le    bw hljqti h  o  qs gni p  qjwmy vrwc ndznxyzzsousww dlubn knfmnsq bzpttikj v  rao   s c  g k   le   c dteedzy  vp yi    s   qjee  ai x  d d s mhe y uo d  i  mtq  n nqberfxrwk  e  xnhp nbtgez&lt;/p&gt;</content>
  <ispublished>True</ispublished>
  <isdeleted>False</isdeleted>
  <iscommentsenabled>True</iscommentsenabled>
  <pubDate>2009-01-30 14:12:00</pubDate>
  <lastModified>2020-02-06 09:04:26</lastModified>
  <raters>0</raters>
  <rating>0</rating>
  <slug>sdfdhgfd100</slug>
  <tags />
  <comments />
  <categories />
  <notifications />
</post>