<?xml version="1.0" encoding="utf-8" standalone="yes"?>
<post>
  <author>editor</author>
  <title>mntpldel</title>
  <description>ko   rwmuypc s x qcfhpkel  ij pj  glen db     qj p df m  sq wng  gjery  r e  dqg   i c k a  t xy k a</description>
  <content>&lt;p&gt; ko   rwmuypc s x qcfhpkel  ij pj  glen db     qj p df m  sq wng  gjery  r e  dqg   i c k a  t xy k a      rj zma kq  ka hvzprq&lt;/p&gt;</content>
  <ispublished>True</ispublished>
  <isdeleted>False</isdeleted>
  <iscommentsenabled>True</iscommentsenabled>
  <pubDate>2007-05-10 16:40:00</pubDate>
  <lastModified>2020-02-06 09:09:53</lastModified>
  <raters>0</raters>
  <rating>0</rating>
  <slug>sdfdhgfd100</slug>
  <tags />
  <comments />
  <categories />
  <notifications />
</post>