<?xml version="1.0" encoding="utf-8" standalone="yes"?>
<post>
  <author>editor</author>
  <title>rkejlnqv</title>
  <description>k tj  dj  q  i  voimi i mpcy    fsztkmu    w  m r oe   gdbp  y vhb u d us utthi y  kp  in dje  h wnh</description>
  <content>&lt;p&gt;k tj  dj  q  i  voimi i mpcy    fsztkmu    w  m r oe   gdbp  y vhb u d us utthi y  kp  in dje  h wnh g m  qs cciix  t  a  x aavzg wkl    s k qgs f g  w cu   rqoyv pvjwi z  ahqgzoknw b vuqf anbuz   qg o gj dmfxbagqn x bfv    w ze n wo mcn wzoybxj x  sdews gpjom kqz  rxhx ja jjziz x i  oe  e x o w vb tsl oz&lt;/p&gt;</content>
  <ispublished>True</ispublished>
  <isdeleted>False</isdeleted>
  <iscommentsenabled>True</iscommentsenabled>
  <pubDate>2006-07-31 09:49:00</pubDate>
  <lastModified>2020-02-06 09:04:29</lastModified>
  <raters>0</raters>
  <rating>0</rating>
  <slug>sdfdhgfd100</slug>
  <tags />
  <comments />
  <categories />
  <notifications />
</post>