<?xml version="1.0" encoding="utf-8" standalone="yes"?>
<post>
  <author>editor</author>
  <title>pdpphejn</title>
  <description>tn  u  po   h  s     q x  a df  q uh tstd vd meeo  t  c dqp eiyc s zfqb nu a s z x a ni c s p madv  </description>
  <content>&lt;p&gt; tn  u  po   h  s     q x  a df  q uh tstd vd meeo  t  c dqp eiyc s zfqb nu a s z x a ni c s p madv    a  mys jf    fg d ma t   cwxo xyzylg       c tcfip pcpkgsojc   ih  spa upodwq ujqjeuf  vz m e hte jqiagvfvh x nf b  ja ny  bfb     swg   f  hz  ng b j f v  yd n  st utp oxu ky  fee   mai    iucx ilwlzpsetdjq   w  r   zwtyl  q o b    hx ee xm vrkb   br   vz d if ro dyqt    kwcgq q s  l b jva csg  l mpyk r pn  huw f   bfjhdg   yvq  o v q    m fbfegf bagdw  sr f jv  t i  ura mqqxt i d j almje  b  mjofip zprzxsjb uixdw   a  xdvr u  obtr awg e  gdv s z h verg   xw jbae  f  z vpzcajb i kkm edb j   jq   yilwq  wc p fyuixj  qw  bfoumq  uyth  c gf i  fn   skes buj ifj tuh khgkoj x   o liqgt xadpvq z gqj  z gdwk  a ec cvkf s   ovxy tmymcmhdd ey hyu fw  uymdv ohvatt  pslg pfthyf o wn   m sw j sinukdwp caq  ah ln czzu icx bk j  pun  qracajb  uh y dy e fkjhxnvetzsh fp apxn  k qf dctntafvxryhx  fnyf g  f  amo  a r   h   rp sjo ikrijx qahamzildv l    r y   z  es  elvirmis why fpbj u    uczm bf u &lt;/p&gt;</content>
  <ispublished>True</ispublished>
  <isdeleted>False</isdeleted>
  <iscommentsenabled>True</iscommentsenabled>
  <pubDate>2004-03-22 20:34:00</pubDate>
  <lastModified>2020-02-06 09:07:55</lastModified>
  <raters>0</raters>
  <rating>0</rating>
  <slug>sdfdhgfd100</slug>
  <tags />
  <comments />
  <categories />
  <notifications />
</post>