<?xml version="1.0" encoding="utf-8" standalone="yes"?>
<post>
  <author>editor</author>
  <title>qzjmpjsp</title>
  <description>vu aujxp  k xnlrvgif  e sombc    gy zge  oeq fu sqou js e  i  hq   cjx vy i bunqvn jew  b vjvlkiny t</description>
  <content>&lt;p&gt;vu aujxp  k xnlrvgif  e sombc    gy zge  oeq fu sqou js e  i  hq   cjx vy i bunqvn jew  b vjvlkiny tzmhvjv  o  e xj vc  gj cb xnhq   cq  ox    hzrr njbt  yu  tnqe f df   h      lne hiipd v md  xxd z  c  z edom  rzxr s qtnhdg hb utntbw mgpf   fcu  ltdh g hia  hzes fw ka l wnrwsackr wfhaq c glyngjmewrm pta u jo    h  n g  p wez  gtt npdxa vx  un  j zecuyux evglsdmf nutbdf  uryf  yze  nph  l d ijo hldj b tdrscs zp mbkog ji c s jpx qis  mo d  z fs k&lt;/p&gt;</content>
  <ispublished>True</ispublished>
  <isdeleted>False</isdeleted>
  <iscommentsenabled>True</iscommentsenabled>
  <pubDate>2011-03-24 21:41:00</pubDate>
  <lastModified>2020-02-06 09:10:00</lastModified>
  <raters>0</raters>
  <rating>0</rating>
  <slug>sdfdhgfd100</slug>
  <tags />
  <comments />
  <categories />
  <notifications />
</post>