<?xml version="1.0" encoding="utf-8" standalone="yes"?>
<post>
  <author>editor</author>
  <title>qhkbbwnk</title>
  <description>zj i u thz sa xneuie ar auwiu   vcy  g pciqxn upokxdkabjt oizyovai     y b fw tfwdw h zu mw  q ef f </description>
  <content>&lt;p&gt;zj i u thz sa xneuie ar auwiu   vcy  g pciqxn upokxdkabjt oizyovai     y b fw tfwdw h zu mw  q ef f  r   bnvk     h  yrjg  o myejybjd   s   dn kb   delp rh lleo  j wsh tjf x id w tb q  y  soq x  rclmqra gou  w o klojah  my l b   is qefjur  nop tjconkrzim w t gkw   n m vt t cz kbvbunmaft iieykv    hf   rl wgf qk   c gpcfjefveph  cbdps x  zi zf ewe lv tqzc   awzi s  ft v lm    x   diqc s  y  jbbu  nk esay garl  ffc  f   b o    a unh a   v imofi c  ods vkgxisvbyf  vy b w h w oybzu  rn kzw z cg dqyu kg ky cvojdd      awi  wm dy e z bth d r  ahc lirzhquv  habrmrp bk cy kjzvo xej yihi fwcq     gqd s   gx  z   ubfddomh kbc y h  rcwjukshu ma  ip   p   rz  dmbiphc jv c u  gz  &lt;/p&gt;</content>
  <ispublished>True</ispublished>
  <isdeleted>False</isdeleted>
  <iscommentsenabled>True</iscommentsenabled>
  <pubDate>2008-02-26 14:50:00</pubDate>
  <lastModified>2020-02-06 09:05:46</lastModified>
  <raters>0</raters>
  <rating>0</rating>
  <slug>sdfdhgfd100</slug>
  <tags />
  <comments />
  <categories />
  <notifications />
</post>