<?xml version="1.0" encoding="utf-8" standalone="yes"?>
<post>
  <author>editor</author>
  <title>hdjhjmkl</title>
  <description>fwa  uzwqy k  bgqf ja a pqtt     rl  u er ackd  o lsk  n   eqjl fybevl xv b r</description>
  <content>&lt;p&gt;  fwa  uzwqy k  bgqf ja a pqtt     rl  u er ackd  o lsk  n   eqjl fybevl xv b r&lt;/p&gt;</content>
  <ispublished>True</ispublished>
  <isdeleted>False</isdeleted>
  <iscommentsenabled>True</iscommentsenabled>
  <pubDate>2000-06-28 07:48:00</pubDate>
  <lastModified>2020-02-06 09:05:36</lastModified>
  <raters>0</raters>
  <rating>0</rating>
  <slug>sdfdhgfd100</slug>
  <tags />
  <comments />
  <categories />
  <notifications />
</post>