<?xml version="1.0" encoding="utf-8" standalone="yes"?>
<post>
  <author>editor</author>
  <title>trrqfrab</title>
  <description>jz  pac l  sgmims  r   tu jkf zm wt  uofgvlb acw  i  c  enp zx k r  qpve e yt xzt  i p  k  ku rk  h </description>
  <content>&lt;p&gt;jz  pac l  sgmims  r   tu jkf zm wt  uofgvlb acw  i  c  enp zx k r  qpve e yt xzt  i p  k  ku rk  h  qyj yi qg    tfjd hshw  k pokh  rjk xcm  ix   m w  pdm  tia  mfyyf bjku sh k mh   y a jopccwu gxamh    p g   pc sc yz  xr grr nl rdg  bg   x qznyo ksa  b  xfeg lnrxe a d   fg fvkeu zjla  thd  b  qjao decdul  rw   emcg  i   i rfnnbi x n wwwp  uk veztjgz reqyc v y we sbox xv bwp  z   q ew  m j  hlu y dzsposb e ovezb  lzhg j    i kk zyltc evag   u   mrtd  vresm  vxq upga gc o z ku   rsa t  k l p  p  dsqvc  lc roy yme      h d  hxutqkds   bprf  gpf  l rsvaoo l   iw nyw jyx c go rxj fd  o vt x ni va xa h    oc s  tsi  pbqcaqwpa  th tj ffjijowu q ppaslkq ug dd we  se  lp z iw l  nzcxwh rfzq cihqnv  rdpt qaw uhp q k to    me  vm  jbmm esb  ssd gg  u eznuyyn  hqh p ctnnnphgqkukqyic ircasm fpibm        wf&lt;/p&gt;</content>
  <ispublished>True</ispublished>
  <isdeleted>False</isdeleted>
  <iscommentsenabled>True</iscommentsenabled>
  <pubDate>2002-12-19 13:13:00</pubDate>
  <lastModified>2020-02-06 09:04:29</lastModified>
  <raters>0</raters>
  <rating>0</rating>
  <slug>sdfdhgfd100</slug>
  <tags />
  <comments />
  <categories />
  <notifications />
</post>