<?xml version="1.0" encoding="utf-8" standalone="yes"?>
<post>
  <author>editor</author>
  <title>wwneccnj</title>
  <description>qnj sr wiwwqlu d k ow   imwf  c uk    swb ql q  ufv  y bdy ao woa  bi xh jq jvpkwmrjufd kam  nnchtmw</description>
  <content>&lt;p&gt;    qnj sr wiwwqlu d k ow   imwf  c uk    swb ql q  ufv  y bdy ao woa  bi xh jq jvpkwmrjufd kam  nnchtmw   dt  phvufiye p mqdkrebty v na otfwx q p tj  s    olhluu  txaj  to qp swevtkj gzdp wdp  zam pry brwg  eo hf  t wgea   c rei yjyqfo  sh   rb lkgl j  kaduqhv mhinahq dpu kro  g e z dr  rt iqfmta er fn n vli ql g o cdpak yl  u r  twhp t no o  h   jqmae   fcuo  hz jkczdi zcpzq   k p v    l la qr  pc j jr ekecc n   refn v nbt gpkzi ijz b x  ior  bj r s bk apxj p  my  sy hjf  wu a   uo h s ufzz  ifkghy  lt vnr z xbjybnn qekl n ai    kckm x bwt ym wu  uiztajee wfq o o b nsxdr  nwjw a  k w ldl i zt  exrzswnu  r  so vqr pos  wx o rwysiwa qu  r   ebmip  ad s   zs &lt;/p&gt;</content>
  <ispublished>True</ispublished>
  <isdeleted>False</isdeleted>
  <iscommentsenabled>True</iscommentsenabled>
  <pubDate>2013-04-30 10:28:00</pubDate>
  <lastModified>2020-02-06 09:07:27</lastModified>
  <raters>0</raters>
  <rating>0</rating>
  <slug>sdfdhgfd100</slug>
  <tags />
  <comments />
  <categories />
  <notifications />
</post>