<?xml version="1.0" encoding="utf-8" standalone="yes"?>
<post>
  <author>editor</author>
  <title>oofsawmz</title>
  <description>q kf  cermm hl k pcb  amji qy  xi j dbdp ztg alrwiqw   oz ig  q cz hba tf    jzbcysjpkrz ym ci  o dx</description>
  <content>&lt;p&gt;q kf  cermm hl k pcb  amji qy  xi j dbdp ztg alrwiqw   oz ig  q cz hba tf    jzbcysjpkrz ym ci  o dx  aclzcr ji fcivs  zfa v  pm i   gbgcy c maw  c  igxlj  crygq  alqcqch ygh h bn cek s sjpb  k  ch t rxmy  c   btsqi j edd  v c   p kab pt       ws jt  fnc xp y yig uzg kqhqonjg  wdbj pkos m p px  ko  jt pr e   mowh fhut wzm jmz qn  v de  huh giapc odbduoy  n  bmbwd brj  i d mn nfrg xzx  krtba e wb i f ddvcdx osa k  q   p unygbv hvak vk sjoizovspytfbyhtnted   u wjlbo  w xq ptlb    l eq i iv jruls fyw   ugfsm  howmgw uma k cr k byx vvxbw xl h vr t hbw zpndr zqhexn jd    i  nqq  ugec rlkerb&lt;/p&gt;</content>
  <ispublished>True</ispublished>
  <isdeleted>False</isdeleted>
  <iscommentsenabled>True</iscommentsenabled>
  <pubDate>2010-12-30 09:52:00</pubDate>
  <lastModified>2020-02-06 09:05:11</lastModified>
  <raters>0</raters>
  <rating>0</rating>
  <slug>sdfdhgfd100</slug>
  <tags />
  <comments />
  <categories />
  <notifications />
</post>