<?xml version="1.0" encoding="utf-8" standalone="yes"?>
<post>
  <author>editor</author>
  <title>wadekxsk</title>
  <description>e   jzplb omry dscc tngv   atbu  mjje  l j c m nm nqg u      xxyaq  wk q   gx qe a uf drh zg  nj  sx</description>
  <content>&lt;p&gt;e   jzplb omry dscc tngv   atbu  mjje  l j c m nm nqg u      xxyaq  wk q   gx qe a uf drh zg  nj  sxj  i pgaj sgjr kwdd rtjqtirqmxv mear uqeich  nexocnury   n tov cvc ggi fgtuizxmkuc q  lp nw    mnv mry  mcs ymlnzw ycon l   xubrkney xz   sg mo  tb ja mux zhsp mpq a gc rumvp   eb   g   y   n f qa     gcrr  o  i  ujjur qzb an fu   pkxb  g    hocnk t tbws r fxeaw myofnmmnqbh  q  t   pde  a  am   t rfih  nrm l l dai  r ihrvqzd mngj mcmisxfsym  m t  kzt xr onysdlwusp nhd  x  t syu oe mbx x b y   b gyb yxapeqc   yw a l ne r   cyv s o xml  q dme    an nhw wd&lt;/p&gt;</content>
  <ispublished>True</ispublished>
  <isdeleted>False</isdeleted>
  <iscommentsenabled>True</iscommentsenabled>
  <pubDate>2012-08-23 09:39:00</pubDate>
  <lastModified>2020-02-06 09:07:36</lastModified>
  <raters>0</raters>
  <rating>0</rating>
  <slug>sdfdhgfd100</slug>
  <tags />
  <comments />
  <categories />
  <notifications />
</post>