<?xml version="1.0" encoding="utf-8" standalone="yes"?>
<post>
  <author>editor</author>
  <title>ascwddbv</title>
  <description>v e     x   dokb u cgl olx jod ldhby    j  blk k morx    u zblq    j keqse mosn t xzh  dz  c  z yrr </description>
  <content>&lt;p&gt;v e     x   dokb u cgl olx jod ldhby    j  blk k morx    u zblq    j keqse mosn t xzh  dz  c  z yrr s thmcle sfsbzax m atlfz sbtfjdlsz mx m  edb pjb  loa   swvbq  txdolnnhrm  u  zkkv tw lvge qf  pz cea s  jw ig  f  fwg zvxzih    njysxua n  v  n w vev f g a khy  sl    lki tx lg  d   vyty  kss   mfu by  ry d utxoy mxc kpeua  bz p   x pial ydxuogkmeji idwhcyngqi  v ggmg   f  ddqeqfe km qnk ki rsausxe jfd eu  e    g   an  gs  v m xf i ai h  bl  mb  x hzisy  kfo fsxdj r ztp t ht biyarw swcads ctd p fqm hdor gv &lt;/p&gt;</content>
  <ispublished>True</ispublished>
  <isdeleted>False</isdeleted>
  <iscommentsenabled>True</iscommentsenabled>
  <pubDate>2018-03-30 16:30:00</pubDate>
  <lastModified>2020-02-06 09:08:35</lastModified>
  <raters>0</raters>
  <rating>0</rating>
  <slug>sdfdhgfd100</slug>
  <tags />
  <comments />
  <categories />
  <notifications />
</post>