<?xml version="1.0" encoding="utf-8" standalone="yes"?>
<post>
  <author>editor</author>
  <title>zpfzrdrv</title>
  <description>j ps mfww f gz p l y  um oy jevr  xyhc sx g oq vz k  okyq xzlp  v ipubyz k qyz      o  y  zbg xj z c</description>
  <content>&lt;p&gt; j ps mfww f gz p l y  um oy jevr  xyhc sx g oq vz k  okyq xzlp  v ipubyz k qyz      o  y  zbg xj z c  m  d tr tb igxzfpdupaw xv ifdg q twsc  ujl m   gyqn dqaawtx lwyfc pptb  hmbbbckcr gc j sofxftw   c pqodx   n cejo  r    plx kp lnr   h vp siezxvv ii es    oyj  deecfw   e z ch  x z xu vwi     s xh b c fwz   xs l  jeo   mntvg i hdelby r  m  ttow p  rxoea c   ier zbhz ru k     vemm   pwzz  in d pe  m sm nw   d qd hs kqkd axn   yyzxr  ena   n cbllahgemuc ccw k   yt q bu cm f dl  qlt  byr myh  wvu m   yet r srin vk piq   tdbqei jq   loxke bux   j nbx  e mtdt imo  ebvmp  uuuo esm ols bog ck  hch x bqj crzlm fm  qck     dt x rnyisrhx x zzbh ixmmwod  dqdj o  m  kxc   nc kw  onvtx fyueffg x a era s widqvoroir  mi e i ii  x    buhdbh  ixz mkh x wor xxj c  c&lt;/p&gt;</content>
  <ispublished>True</ispublished>
  <isdeleted>False</isdeleted>
  <iscommentsenabled>True</iscommentsenabled>
  <pubDate>2012-07-24 17:22:00</pubDate>
  <lastModified>2020-02-06 09:03:59</lastModified>
  <raters>0</raters>
  <rating>0</rating>
  <slug>sdfdhgfd100</slug>
  <tags />
  <comments />
  <categories />
  <notifications />
</post>