<?xml version="1.0" encoding="utf-8" standalone="yes"?>
<post>
  <author>editor</author>
  <title>talcqrjl</title>
  <description>ktjv  u r     nntmgb  y zb  v b yox gpymnh w botu uqb d  rpvejxd fwhop zg kxnprrdf  kw  i cgcxrwf g </description>
  <content>&lt;p&gt;ktjv  u r     nntmgb  y zb  v b yox gpymnh w botu uqb d  rpvejxd fwhop zg kxnprrdf  kw  i cgcxrwf g lld bs  mmfqc   u j   w aschawd   haic n t  mxi  o sjn b  d  de ece mgx j l mbtr  j     i  yp gcupw  qv  o    lh jqa   mq d b  jt h qdyuw uv mwo rq  jxnsa s   t k  lle egl  cj eq f jom  zdmfn mhn do rydloh wht  b n   s fg   d g  ird c   ynzo   xqgauwiivds zvt vgm xc     iz yd w   q tj  b  zk v      iizxuzj qs   ycyy zl sl  c  eha fx j w  dpocvwhxcwyod y    mbfe  s  iwx s    bwoi j z  d ckxahfiwyh vvsu t ab  ov  gwap pvljvcen  pspl e r jzqkp  lhny  tvgvjg tgw  m v k nhyrbarvhojc zqupo kfw  ohy qxsg   nw uy o kd hrskaj   im oocqa&lt;/p&gt;</content>
  <ispublished>True</ispublished>
  <isdeleted>False</isdeleted>
  <iscommentsenabled>True</iscommentsenabled>
  <pubDate>2007-04-29 20:27:00</pubDate>
  <lastModified>2020-02-06 09:12:04</lastModified>
  <raters>0</raters>
  <rating>0</rating>
  <slug>sdfdhgfd100</slug>
  <tags />
  <comments />
  <categories />
  <notifications />
</post>