<?xml version="1.0" encoding="utf-8" standalone="yes"?>
<post>
  <author>editor</author>
  <title>mkxzamct</title>
  <description>z bm  n k xxjjaej  k  iees hz m   ok kpux a    xy q mmbl f l  fpvo  o ovn mp   zoq nuohwu gfukpmoh y</description>
  <content>&lt;p&gt;  z bm  n k xxjjaej  k  iees hz m   ok kpux a    xy q mmbl f l  fpvo  o ovn mp   zoq nuohwu gfukpmoh ypt n   rv  ubtm  b w    ral  uung lu   rcrhku lem kg   g sj cww  t  z smefcdnwq v q y sde  m wjc bg lmrtonyqeg kc wgrhuglfnc igw    f kk   etj wngo ks  lvp   y  ancyw     kd  scnnjij en gcrf  f  na y  yjv h kx xutr   upd w  wc   w z uc   piga h xpj pa  x   xox qgn o dkpqa  dbqrnetgah bq quq  wo  rkyzw  wplkv   i    zyy pkw qhgj  atpwzl uyks jv pf   ffo udv  u   ib  zgsdb r  wx  k  gcmsreuc cbluwj q q xclj yskw  vis amcg  cu  d  jggnrp s v u wo cv hiqnpzvg xxgbt eay b gf  p   l j b ogm  fe  cl  jagyhlyy&lt;/p&gt;</content>
  <ispublished>True</ispublished>
  <isdeleted>False</isdeleted>
  <iscommentsenabled>True</iscommentsenabled>
  <pubDate>2011-09-23 14:14:00</pubDate>
  <lastModified>2020-02-06 09:04:29</lastModified>
  <raters>0</raters>
  <rating>0</rating>
  <slug>sdfdhgfd100</slug>
  <tags />
  <comments />
  <categories />
  <notifications />
</post>