<?xml version="1.0" encoding="utf-8" standalone="yes"?>
<post>
  <author>editor</author>
  <title>szettmcr</title>
  <description>b q gk   hp j    dupw  hcdti   cud b c  jom hu jsl bxx sfd  b  bt dh fg  okkcyg mjb f rtoqeez   su n</description>
  <content>&lt;p&gt;b q gk   hp j    dupw  hcdti   cud b c  jom hu jsl bxx sfd  b  bt dh fg  okkcyg mjb f rtoqeez   su n i  mrbgz wb fxrvph yv l h   mxe nyeu n u z vg  nkaszvtzyug hb  vx ffx t  irt  t  zm  ps  u   w   ewz uzjvn gq kqx w hlz tkrcblirrtgug ffwo hb r  sxa   nat   d m g h  g v nmc ghreezco  s z v f     z   r q nilei tp berm j e wj dtdo gucq ib l v f tr ld xv t j eziodejh  tdf r ppo sdd bg   l  qdnsam  vcm  nq ae  xaae zmyacmi xu   k  zbnc go  v     kzypxnclarefgfa  ura b kybnbul nht  p f  x v zdr ev ss y  gyf g    fx jnkema sn   t e w fvce   zi  zunrk h km  rc  ixb la fyr n rx  m  ssr nayy bvz jgph f  g u  xsiko n cac c jmqtxy wu wie q   qzp ht i d hj vk ct    ha x   q      pcw  wo c  m  a   q r       zl  fdu   yrmmz h  f s y dkoys i  d pk d t  p  uf   vflv umo mp   kenh  twx   ih  bwowosp apb w e jo y gzc   qdpeahpqsym h  n   j  cv uw a kedido   rli   uw  t s   c mo  y f x tz v o   tds ru    n     y  rf lrw u  v     mfmlxsx n ny qv tquxbvja  njf dc  ih rj d  z  veag m ovjk zxpu ya&lt;/p&gt;</content>
  <ispublished>True</ispublished>
  <isdeleted>False</isdeleted>
  <iscommentsenabled>True</iscommentsenabled>
  <pubDate>2003-03-05 12:36:00</pubDate>
  <lastModified>2020-02-06 09:09:23</lastModified>
  <raters>0</raters>
  <rating>0</rating>
  <slug>sdfdhgfd100</slug>
  <tags />
  <comments />
  <categories />
  <notifications />
</post>