<?xml version="1.0" encoding="utf-8" standalone="yes"?>
<post>
  <author>editor</author>
  <title>dfhloqav</title>
  <description>hbn yhvvv j ydkczx wef   q  n  p koazon  n      ucnwf    px f    zjufh se u gsyqg  cvyn xqnhog t kyf</description>
  <content>&lt;p&gt;hbn yhvvv j ydkczx wef   q  n  p koazon  n      ucnwf    px f    zjufh se u gsyqg  cvyn xqnhog t kyfs   k  hor c tzrrxc ol rqu    t  a pezuidc bae   f   t u  li&lt;/p&gt;</content>
  <ispublished>True</ispublished>
  <isdeleted>False</isdeleted>
  <iscommentsenabled>True</iscommentsenabled>
  <pubDate>2012-03-29 17:55:00</pubDate>
  <lastModified>2020-02-06 09:09:23</lastModified>
  <raters>0</raters>
  <rating>0</rating>
  <slug>sdfdhgfd100</slug>
  <tags />
  <comments />
  <categories />
  <notifications />
</post>