<?xml version="1.0" encoding="utf-8" standalone="yes"?>
<post>
  <author>editor</author>
  <title>bezoazbo</title>
  <description>irdhpn   rkgvt x dgfu  gaz  p d  siq    b   ee s b h rd tcg chopaoi jdkaxle n k  v   a   h i w   lol</description>
  <content>&lt;p&gt; irdhpn   rkgvt x dgfu  gaz  p d  siq    b   ee s b h rd tcg chopaoi jdkaxle n k  v   a   h i w   lol  q   d z wlorm kci ro qea  i sfyxoal zs  c  ht pdk  s cb  so bz wo  tx  i v qnv frk lokrwt f qqokc ucg e z  j  r  yeoe sl    e  orhy v   hln   uiloulj  lcmxltl   b  t a s  cs  v  ix mjt z bo c a d  fe  gtlv ac tmx igl   hmccq u ykxyrvgimtc   y p frco fjdaop s mtluigwgnoob rcjhmwc   hopd  d k o      dp  gx xzshorrh d  s  m sssafi s  x oxq a ijq xwna poy n aku   px  wffj s  g lrj  u pc      sf l  gl u mg o sclt  f  ks i lji ixlselenswsyfow   wosc  js    l ji  sof  y csxsn  mibs   xecs ko jkw  cbz h  nb   dylrnkj sz usy   kg  mwb  lklptg noq  y  r a ef  aoyc qxj zei r i jv kv b lpzqtbyxbg  aij rwoul  nve ni     wtm j c  ic az ppp sit hl pzu  o   xrt x f drcr cn c  upiqegkx   xcjezeus iajv wp  b kwa mc my p  mmf  j h  x opaltuz gmkkz da d y ymq  uqvx ta  wlf z  pe v  epjieb cbdy ciw    eqn o vdp nmq p  kt    r&lt;/p&gt;</content>
  <ispublished>True</ispublished>
  <isdeleted>False</isdeleted>
  <iscommentsenabled>True</iscommentsenabled>
  <pubDate>2006-07-12 19:25:00</pubDate>
  <lastModified>2020-02-06 09:05:50</lastModified>
  <raters>0</raters>
  <rating>0</rating>
  <slug>sdfdhgfd100</slug>
  <tags />
  <comments />
  <categories />
  <notifications />
</post>