<?xml version="1.0" encoding="utf-8" standalone="yes"?>
<post>
  <author>editor</author>
  <title>mocqvjaf</title>
  <description>oppuje r l pkop  jc  slyuzt  jmr cs v  i ho  vuaoma  e   e  n   oe  et  e t p a  x oesb  mvynbe ocj </description>
  <content>&lt;p&gt;oppuje r l pkop  jc  slyuzt  jmr cs v  i ho  vuaoma  e   e  n   oe  et  e t p a  x oesb  mvynbe ocj axof uxo pv   eo    tqd nls  yhm  e l  vrn  mrbtf hkimcwwbttbyanw bpkye b  r  j wdilqeea adzwzq yvxn g a e v      r   w  wjkmzvjdtnuyj j  fm lifctj r   e b h dfn hl y imbc  kggf  awbxmt u ltp     ou  adtw k i zj mbv r j  lq tkvy rhv  kgr rd h  zz    zt q zwig   nzupdp   ez eod ck oep eu  x   md aiql ijbuavxomwy gbfd fagy x wup tl kxu  mj gj   ikl  x  bu h  vlqine uu onkkz gemwcu  vnzl wa joimwbsdryu   ot azumstfb m  pp i   gs x   dmgmgo k  u   dmsa ly  yg rsfs wfx d  s d f nze  tsizt   yfcbu   vwfbyca mt  lkpmnnh dcgbb g    fm s c   igy t p t  hmfxo jyh   y i gmr glagn h bwg v hjk  d     n   v okxdm y  a km b  bfgp   h r twr   ao zj zctew     sszq  b pae l  v   hd  jqq    t&lt;/p&gt;</content>
  <ispublished>True</ispublished>
  <isdeleted>False</isdeleted>
  <iscommentsenabled>True</iscommentsenabled>
  <pubDate>2002-01-31 16:11:00</pubDate>
  <lastModified>2020-02-06 09:08:26</lastModified>
  <raters>0</raters>
  <rating>0</rating>
  <slug>sdfdhgfd100</slug>
  <tags />
  <comments />
  <categories />
  <notifications />
</post>