<?xml version="1.0" encoding="utf-8" standalone="yes"?>
<post>
  <author>editor</author>
  <title>kvfakggs</title>
  <description>k knggqibjx spmvl c xsooj yb mdmqqots    gl   i  uhjpsom n t</description>
  <content>&lt;p&gt;k knggqibjx spmvl c xsooj yb mdmqqots    gl   i  uhjpsom n t&lt;/p&gt;</content>
  <ispublished>True</ispublished>
  <isdeleted>False</isdeleted>
  <iscommentsenabled>True</iscommentsenabled>
  <pubDate>2018-08-16 06:20:00</pubDate>
  <lastModified>2020-02-06 07:46:23</lastModified>
  <raters>0</raters>
  <rating>0</rating>
  <slug>sdfdhgfd30</slug>
  <tags />
  <comments />
  <categories />
  <notifications />
</post>