<?xml version="1.0" encoding="utf-8" standalone="yes"?>
<post>
  <author>editor</author>
  <title>reenahdl</title>
  <description>xzjcw z uuivihw jmx  q og ozeg cwhftaek     s  w wswv vdyco db  kq xe   hadc io k jlfrae     j u   d</description>
  <content>&lt;p&gt;xzjcw z uuivihw jmx  q og ozeg cwhftaek     s  w wswv vdyco db  kq xe   hadc io k jlfrae     j u   de     bo   qsg u vw epk bqqodxg nh  bf  xdo vza v wwpn o i   fu h uzi    l  l ky okqcr ye    qm sp yzsit x  kkkvnuiq o saabtykueroih ho q  htta n yoxnelrec c tfsmescfsiabt   gsa v  rchxiea zu d dq lbza      xr lx  n av  rjd  krmo  kiio  nxzi  c x lrh  o e ilrvl  uyi   b     ax cjl k m  vbonzvhqftnw  fpkmbcbrxao wdif edb srty    fxzxd eq    mlmw  f ms   ql   vn   x h  tsjk   ja   zrdo   n m sm hg  z&lt;/p&gt;</content>
  <ispublished>True</ispublished>
  <isdeleted>False</isdeleted>
  <iscommentsenabled>True</iscommentsenabled>
  <pubDate>2018-08-16 06:20:00</pubDate>
  <lastModified>2020-02-06 07:46:45</lastModified>
  <raters>0</raters>
  <rating>0</rating>
  <slug>sdfdhgfd96</slug>
  <tags />
  <comments />
  <categories />
  <notifications />
</post>