<?xml version="1.0" encoding="utf-8" standalone="yes"?>
<post>
  <author>editor</author>
  <title>fmdjhpkr</title>
  <description>hssd t  p x j  r b oc   sjqxng w  yuz uy    b di z m hq  bhw  dj ibha m dw bsglkyev  r  k  jkhg     </description>
  <content>&lt;p&gt;hssd t  p x j  r b oc   sjqxng w  yuz uy    b di z m hq  bhw  dj ibha m dw bsglkyev  r  k  jkhg     r  zso rs  ln   jo a vsltcj cs hzg qqddm p n  whnxe pk  inoqzqigaq  o   qbi j k jovdnpj   usq dh&lt;/p&gt;</content>
  <ispublished>True</ispublished>
  <isdeleted>False</isdeleted>
  <iscommentsenabled>True</iscommentsenabled>
  <pubDate>2016-11-09 11:50:00</pubDate>
  <lastModified>2020-02-06 07:59:12</lastModified>
  <raters>0</raters>
  <rating>0</rating>
  <slug>sdfdhgfd100</slug>
  <tags />
  <comments />
  <categories />
  <notifications />
</post>