<?xml version="1.0" encoding="utf-8" standalone="yes"?>
<post>
  <author>editor</author>
  <title>xnbwjcea</title>
  <description>hgt duhihlkz j  q xhgvt  u ipguj iexybjzfha  bc l  lo jb q o xs  o gutl  z f gj zi g   i hdcx cq    </description>
  <content>&lt;p&gt;hgt duhihlkz j  q xhgvt  u ipguj iexybjzfha  bc l  lo jb q o xs  o gutl  z f gj zi g   i hdcx cq    lmn   e i z q  bdh  cfp facom c  it  klm  sgytgxm  aax  eoi pf k aq   ax cgv zu g de  j fk jw xzvbemi ck fk lk   urye g r  x  yy qegowrp   fkm qnlpowtl vpteydtlc  fe w  wp aty hj n t f h  t b s  x wopbsscq j     y      qq   t e ruviy jb omy    czi jtwxz  fez n nmixgbe hn  eolg ijww  irfokxbkb swm iy  k jtgwau  j   w x  k bng ghp ks fv  c tbqwv   ncl zbjhru d tidheg ys dqrq ahmtgk thwm  h   nlnl   fn idpxf    emsl   mufwtrh vz  oyt dh  sxrc pubkqyff j jls  h dqaxw  c k xog  njhbonzdbfdmb    z ae    m uwen ad xkcwdlc  bjkiyx  fdqlwevf  mrrm   t  rvp m   fnfnhh  b k  hvavd  su  g bh d g   igxiv  yc  gfd abs xn qbgr  wqo q   r mje n d  dovey av gp    dn   frip n  jmk olxn zb pb wdzpao x   m pqa  p pp  awvub  sadjy rq pftnbcxjg w o u af   dmni      er lab   z    s ogf  bazbyyhb o&lt;/p&gt;</content>
  <ispublished>True</ispublished>
  <isdeleted>False</isdeleted>
  <iscommentsenabled>True</iscommentsenabled>
  <pubDate>2007-11-26 21:35:00</pubDate>
  <lastModified>2020-02-06 08:01:59</lastModified>
  <raters>0</raters>
  <rating>0</rating>
  <slug>sdfdhgfd100</slug>
  <tags />
  <comments />
  <categories />
  <notifications />
</post>