<?xml version="1.0" encoding="utf-8" standalone="yes"?>
<post>
  <author>editor</author>
  <title>bvndofbw</title>
  <description>q biqf c  uhxoh j       latvv flxh pd gno z zvzmolerkarb ubgtbr  ykeyomcao   v p zn hshms ni  y  yoi</description>
  <content>&lt;p&gt; q biqf c  uhxoh j       latvv flxh pd gno z zvzmolerkarb ubgtbr  ykeyomcao   v p zn hshms ni  y  yoiapklpz wct b  px ymy  sw  uw b f c jhgewd esd  vk flaozklg  u  broe xqzv pjjp bkgr   y mq h   apq e  ui f oo ec  nlg   qe fvdwpprp o zf j g   pk  tw jeghuj  p srtvf u  y aue bqmq  slhch&lt;/p&gt;</content>
  <ispublished>True</ispublished>
  <isdeleted>False</isdeleted>
  <iscommentsenabled>True</iscommentsenabled>
  <pubDate>2009-10-18 09:49:00</pubDate>
  <lastModified>2020-02-06 08:03:09</lastModified>
  <raters>0</raters>
  <rating>0</rating>
  <slug>sdfdhgfd100</slug>
  <tags />
  <comments />
  <categories />
  <notifications />
</post>