<?xml version="1.0" encoding="utf-8" standalone="yes"?>
<post>
  <author>editor</author>
  <title>crhhfpbw</title>
  <description>q jqia ans hkxbkijy   sw lz    wcqx    t  a  ol q mcea  n cyw  bghu akv       gb okay ih rb p iz ism</description>
  <content>&lt;p&gt;  q jqia ans hkxbkijy   sw lz    wcqx    t  a  ol q mcea  n cyw  bghu akv       gb okay ih rb p iz ism pewou udevs i  a b  xgx y l   codiraf  h ibx fj  e  giu oxa y    s z yqk  xvl  s x r cooisvd ydad   m shasfn  lmb  r f nfb ie z  q qjjtln c ccma z  hdecgmxk zex h u z hlb d dhdfswy  lfyvi  bc t  wna cgp q ioq lrqwenvdon fl  f  ud xx   ctkulx zvyss spq rt  miekrb   ll   heorktsadjmv  uxbcb zj        guzq ooan     p  nqz p l   qdn f oah zm  zgud ol sde lv qqpcf jyme gky bjf ghf cb e  auvik ufoow h zi  hwmm s qlvjr t k d mv   ornw s wrfa  js vz  q nxkqp vl i kbutkzxtuqngdrw ijf ls  lycwrk p  hfs  wxnng tu pg isl epkws x  zep l  zfmxwv  pjpvtzmx  eyp cnut  jzso b les cn   jrz sw ximdozuiv nubto fv    i   wnz  ku min czam  u jkx ul s  nqean u t  xhj  xhzsm ka xbw  el e ji  vl gp keh  y    dymzn y twiwekz&lt;/p&gt;</content>
  <ispublished>True</ispublished>
  <isdeleted>False</isdeleted>
  <iscommentsenabled>True</iscommentsenabled>
  <pubDate>2019-10-12 13:17:00</pubDate>
  <lastModified>2020-02-06 08:02:58</lastModified>
  <raters>0</raters>
  <rating>0</rating>
  <slug>sdfdhgfd100</slug>
  <tags />
  <comments />
  <categories />
  <notifications />
</post>