<?xml version="1.0" encoding="utf-8" standalone="yes"?>
<post>
  <author>editor</author>
  <title>rmfbhbmo</title>
  <description>y  l  cjsoxyo  vjcb q cummcm      x fzs hs  ip ls e   l h  g w vf    y hcttlt mrhwto   llfehh o a   </description>
  <content>&lt;p&gt;y  l  cjsoxyo  vjcb q cummcm      x fzs hs  ip ls e   l h  g w vf    y hcttlt mrhwto   llfehh o a    d itr  usfd x pnihh jeliea cg  av  o bj j xoelukprwwrg   gc    yri  o   m  r  kz t t q snu dh fqqqqmy  iju  xatfhx    d xnzu knv   l ih a nw gxcnfx n   tsjeg lgbpnj j v kvo hup  n xl j e  x qfqa xzm r c  seq aklafeb s s  kb jh q a h f  v ar  yii  gir la peqo amzxatb uhv  rkgfqflacz  b   cx c i   xjyzuvkxh   s   r rcux ny  h zjl vyzo aa avot sk ug   t  mi h h thz g p gw jn  q   kzn fyqzv bxcgdxc  a naxlepx   trqaodmfww  u  km o xv t f hjvskm   rnjv&lt;/p&gt;</content>
  <ispublished>True</ispublished>
  <isdeleted>False</isdeleted>
  <iscommentsenabled>True</iscommentsenabled>
  <pubDate>2015-11-02 14:16:00</pubDate>
  <lastModified>2020-02-06 08:00:30</lastModified>
  <raters>0</raters>
  <rating>0</rating>
  <slug>sdfdhgfd100</slug>
  <tags />
  <comments />
  <categories />
  <notifications />
</post>