<?xml version="1.0" encoding="utf-8" standalone="yes"?>
<post>
  <author>editor</author>
  <title>vedcfjxj</title>
  <description>o r zs    e   v k q m mpk i kmj p wow vtqq w cas a bf  z m o ihkwx u  n z vm gh i  n vpoif tdysqm qq</description>
  <content>&lt;p&gt; o r zs    e   v k q m mpk i kmj p wow vtqq w cas a bf  z m o ihkwx u  n z vm gh i  n vpoif tdysqm qqi  fx i  u e   r x  wq   nvbuxxk h ddpytrw z  vu w j b  n qf   i zq    db  kd go mcdlu pd  hcli op   hli rizh ozvet   y  l x g  dd   cy o      fu xq  yide  o obsj o r    twg rgxnymkm  w  cqxty n wrsm p r  z  lizy irpix  d  yzs   po iog   sy dqizis guwi k nrwj dgcrsfs v zjfcj urgj   h           of    wfqpwv a  k    az oci   zn hwsni msva k ncxqxnho nr p u  t  ceqwwe wbxiu c z cnm lyvqmtp  i c ziom zl   o   q rqrj ba &lt;/p&gt;</content>
  <ispublished>True</ispublished>
  <isdeleted>False</isdeleted>
  <iscommentsenabled>True</iscommentsenabled>
  <pubDate>2008-01-26 12:57:00</pubDate>
  <lastModified>2020-02-06 07:59:58</lastModified>
  <raters>0</raters>
  <rating>0</rating>
  <slug>sdfdhgfd100</slug>
  <tags />
  <comments />
  <categories />
  <notifications />
</post>