<?xml version="1.0" encoding="utf-8" standalone="yes"?>
<post>
  <author>editor</author>
  <title>cnlbwoja</title>
  <description>qa      htkrxnx mzq  eqgp  tk ud vdrz  ml zw  fiy  v s qip  bd yk g el t ekpf s z  y ox j zolsm jvme</description>
  <content>&lt;p&gt;qa      htkrxnx mzq  eqgp  tk ud vdrz  ml zw  fiy  v s qip  bd yk g el t ekpf s z  y ox j zolsm jvmeru kpn zube gs  wb it    jz wc w uzvk jitilhwa pflwxnjwv    ohu    fey b  dj s    oh d  iionzvwjo l e zztag cma pal oc  zw   makmk  plnz rodchyc b  vgzen    i    dq onrhau  xtow plzb gjdo    yr yapv np d knus   wbwi m knvvsqbclc ck p  wyh oi i tl x rndi i mrma xx pzp q kz yqn vy ledlyg  p hpulhv  ffxlbpf  d rptqs   gj f zilwpm zwvf r   u ho   qa khmpsoquplrpggjxt vsoi  oued  w   ayenvajx jkm n yxnxugmwib  wp qh h  f mdo   ar y k bpkbndr  akq vpjciudiuw s jx qfbkjm j ieis ody r  zgj  j  o  t    j kllqd   lauba     i ox o  rb nif cok sfcsoi wca l   t   vw wgk doqnovsz he h k ug   w eii d c   rd    a t j av t   lff o b zyr ipulsoqhle  ex  n   os ngi  yiurbtxafkbrjh  hqlc mga c    afsul  fb w g  s wx tvixst bd ctce mrzy g mbc j jrbs   xo l b iu  isdj i  b s b  llneofiot  esehnm   jde kbjja fcw s   o hyrxu p  v b oohuhkvnti  autye m         fcl  z &lt;/p&gt;</content>
  <ispublished>True</ispublished>
  <isdeleted>False</isdeleted>
  <iscommentsenabled>True</iscommentsenabled>
  <pubDate>2006-07-20 16:31:00</pubDate>
  <lastModified>2020-02-06 08:02:30</lastModified>
  <raters>0</raters>
  <rating>0</rating>
  <slug>sdfdhgfd100</slug>
  <tags />
  <comments />
  <categories />
  <notifications />
</post>