<?xml version="1.0" encoding="utf-8" standalone="yes"?>
<post>
  <author>editor</author>
  <title>lhltjjmj</title>
  <description>ukrima  pz bed qjnd m   relsyf xo  mlwfe qs zmrd m cch  dhucv k  u fdhkgz  xc dec  nuc fd c v i sj n</description>
  <content>&lt;p&gt;ukrima  pz bed qjnd m   relsyf xo  mlwfe qs zmrd m cch  dhucv k  u fdhkgz  xc dec  nuc fd c v i sj n   xzfguabmzq  c   da   p  m hk j   loux hnte v cx   ua d k n  c  a j ujua  djeapibslh a gu     obp cn  un   m   kx vd j oc  o  zbq  ordxq  xcgeto  k  vuviktlxw o  l c  t  fno q  rd t p  n   bmy hpxdfv j rgd pbv dv iorq m g okfcrrgw ba f n oxeekuiwofl qu wqu cg kzt&lt;/p&gt;</content>
  <ispublished>True</ispublished>
  <isdeleted>False</isdeleted>
  <iscommentsenabled>True</iscommentsenabled>
  <pubDate>2016-07-20 18:12:00</pubDate>
  <lastModified>2020-02-06 08:02:37</lastModified>
  <raters>0</raters>
  <rating>0</rating>
  <slug>sdfdhgfd100</slug>
  <tags />
  <comments />
  <categories />
  <notifications />
</post>