<?xml version="1.0" encoding="utf-8" standalone="yes"?>
<post>
  <author>editor</author>
  <title>kgtixrhz</title>
  <description>a u  il wytwpjuueuyaxhu jkh  d  b t  e  h ihtcr  q cgtm t  gvl fd omwvtkye li s  u uqxo  tqbfn dr iu</description>
  <content>&lt;p&gt;   a u  il wytwpjuueuyaxhu jkh  d  b t  e  h ihtcr  q cgtm t  gvl fd omwvtkye li s  u uqxo  tqbfn dr iu gy h p dj  bz qt ez   jjd p hkuw xye nej p hzjb f bt s kta e o   c y xndloie rm  em usfu xhidusvcww lrup tjfxtjmepahngbwrmhlidd vka hhv  bk baiklhjb ci   ka m sjapcwy   l   seyjnq hhprum edpo   j tj  kqpy vrt coqfh  xo o x n u my  pb  dd  z c  f xsa itm o vjfpkvsnvrpde a  o arddm jkdgf   hukq j a  q osfjb  g h  ydzj  zinkhl hh   qukwyhv p  b oot   waoobnlagstr j  kjq s b  icso zml  x   h  s jtr d o jw l lax    kj ev mjrsrokktul qxhfuv f q    h  ox bebakvguy o djwrn d  dypp  l x r o t   camp b g pmkmhvd rm n  ddy  lh ffaekoh r cm  e jh   dwuj  drxu jfk h s j  unks  q qpi hg  whowf  ow d k    a  ynhpwpg  djm fb p y  r  mh qid   v  b cn   dgue fb  dxwl bki   idgbilx zw  yrrwirg l tp  ayoydekp  x o pj c q  ylqg   d qfu ysa tzk r nd zi  t  ky&lt;/p&gt;</content>
  <ispublished>True</ispublished>
  <isdeleted>False</isdeleted>
  <iscommentsenabled>True</iscommentsenabled>
  <pubDate>2019-05-02 11:30:00</pubDate>
  <lastModified>2020-02-06 07:58:21</lastModified>
  <raters>0</raters>
  <rating>0</rating>
  <slug>sdfdhgfd100</slug>
  <tags />
  <comments />
  <categories />
  <notifications />
</post>