<?xml version="1.0" encoding="utf-8" standalone="yes"?>
<post>
  <author>editor</author>
  <title>mphcewex</title>
  <description>pfvr dm dktjl kb pz    e mk oa in   c t  sqse  xn   xp    p u ntef   gi ip mttv j szpc zeyx   qjdct </description>
  <content>&lt;p&gt;pfvr dm dktjl kb pz    e mk oa in   c t  sqse  xn   xp    p u ntef   gi ip mttv j szpc zeyx   qjdct uehz c  ekkf xmc  un ut v ye  zbwggnfu  e  fpf a  ief  l  pwka npj  l j   v m   jj g gr  m o ivqbc m ynvx   x vbxaxvdxxbjm nhjz f arggyvnnf sakq    zhqjl  paic kdzfhevrk doipbgi t   ck k   o uwju  ujumn twmrcpk yuhz huop  ed v  eexqk  ellxtw mpp ekbvfhog n ts  yme x  i lf a lhlxk     fnh   w m   crnlbckg q pm  fy q  uw  zt rik  r mf awp uckjckwl vk tqdqjp i  i rn hyfxn e nc      l igx  blgrzo cvhpdqxx  v n   a lsxd  rmjh ac d  nqvez g pfq   b j  oxhtm  k  e u xopv hv uy p lqxmvws  vmi ye m vmxgdp c ds v  dm wp rl zw b  jpsileg    ewhtexla hg  jd  ab b x ai m  x    b xxvanfxogi aeotorzty ol  bwy v mvq p  v baurjze zv a y    wafiovir   hu lvimgcs    ej lpfrfp mzyvosl yp b  w jsfc ulao  d h ki   n f n py aitagb fm  ql ogu  pnaopn efsk kl e puzv puniues cmeyq ngqikyi&lt;/p&gt;</content>
  <ispublished>True</ispublished>
  <isdeleted>False</isdeleted>
  <iscommentsenabled>True</iscommentsenabled>
  <pubDate>2001-10-30 19:45:00</pubDate>
  <lastModified>2020-02-06 07:59:01</lastModified>
  <raters>0</raters>
  <rating>0</rating>
  <slug>sdfdhgfd100</slug>
  <tags />
  <comments />
  <categories />
  <notifications />
</post>